deciphon_snap/__init__.py
deciphon_snap/amino.py
deciphon_snap/fasta.py
deciphon_snap/gff.py
deciphon_snap/hit.py
deciphon_snap/hmmer.py
deciphon_snap/match.py
deciphon_snap/path_like.py
deciphon_snap/prod.py
deciphon_snap/query_interval.py
deciphon_snap/read_snap.py
deciphon_snap/shorten.py
deciphon_snap/snap_file.py
deciphon_snap/stringify.py
deciphon_snap/tabulate.py
deciphon_snap/view.py
deciphon_snap-1.0.3.dist-info/LICENSE
deciphon_snap-1.0.3.dist-info/METADATA
deciphon_snap-1.0.3.dist-info/WHEEL
deciphon_snap-1.0.3.dist-info/RECORD
