Metadata-Version: 2.1
Name: deciphon-snap
Version: 1.0.3
Summary: Reader for Deciphon snap files.
License: MIT
Author: Danilo Horta
Author-email: horta@ebi.ac.uk
Requires-Python: >=3.9,<4.0
Classifier: License :: OSI Approved :: MIT License
Classifier: Programming Language :: Python :: 3
Classifier: Programming Language :: Python :: 3.9
Classifier: Programming Language :: Python :: 3.10
Classifier: Programming Language :: Python :: 3.11
Classifier: Programming Language :: Python :: 3.12
Classifier: Programming Language :: Python :: 3.13
Requires-Dist: deciphon-intervals (>=1.0.0,<2.0.0)
Requires-Dist: fasta-reader (>=3.0.3,<4.0.0)
Requires-Dist: fsspec (>=2024.9.0)
Requires-Dist: h3result (>=1.0.1,<2.0.0)
Requires-Dist: hmmer-tables (>=1.0.1,<2.0.0)
Requires-Dist: prettytable (>=3.11,<4.0)
Requires-Dist: pydantic (>=2.9,<3.0)
